go_contacts-0.1.9.dist-info/METADATA
go_contacts-0.1.9.dist-info/RECORD
go_contacts-0.1.9.dist-info/top_level.txt
go_contacts-0.1.9.dist-info/metadata.json
go_contacts-0.1.9.dist-info/WHEEL
go_contacts-0.1.9.dist-info/DESCRIPTION.rst
go_contacts/__init__.py
go_contacts/server.py
go_contacts/tests/test_server.py
go_contacts/tests/server_contacts_test_mixin.py
go_contacts/tests/__init__.py
go_contacts/tests/server_contactsforgroup_test_mixin.py
go_contacts/tests/server_groups_test_mixin.py
go_contacts/handlers/__init__.py
go_contacts/handlers/contacts_for_group.py
go_contacts/backends/groups.py
go_contacts/backends/contacts.py
go_contacts/backends/__init__.py
go_contacts/backends/riak.py
go_contacts/backends/utils.py
go_contacts/backends/contacts_for_group.py
go_contacts/backends/tests/test_contacts_for_group.py
go_contacts/backends/tests/test_contacts.py
go_contacts/backends/tests/__init__.py
go_contacts/backends/tests/test_groups.py
