Metadata-Version: 2.0
Name: go-contacts
Version: 0.1.9
Summary: A contacts and groups API for Vumi Go
Home-page: http://github.com/praekelt/go-contacts-api
Author: Praekelt Foundation
Author-email: dev@praekeltfoundation.org
License: BSD
Platform: UNKNOWN
Classifier: Development Status :: 4 - Beta
Classifier: Intended Audience :: Developers
Classifier: License :: OSI Approved :: BSD License
Classifier: Operating System :: POSIX
Classifier: Programming Language :: Python
Classifier: Topic :: Software Development :: Libraries :: Python Modules
Classifier: Topic :: Internet :: WWW/HTTP
Requires-Dist: cyclone
Requires-Dist: go-api (>=0.3.0)
Requires-Dist: vumi (>=0.5.4)
Requires-Dist: vumi-go
Requires-Dist: confmodel (==0.2.0)
